fluxpoint/__init__.py
fluxpoint/client.py
fluxpoint/errors.py
fluxpoint/http.py
fluxpoint/py.typed
fluxpoint/vars.py
fluxpoint/paths/__init__.py
fluxpoint/paths/color.py
fluxpoint/paths/convert.py
fluxpoint/paths/imgandgif.py
fluxpoint/paths/lists.py
fluxpoint/paths/minecraft.py
fluxpoint/paths/misc.py
fluxpoint/paths/test.py
fluxpoint/paths/utility.py
fluxpoint_py-0.2.0.dist-info/licenses/LICENSE
fluxpoint_py-0.2.0.dist-info/METADATA
fluxpoint_py-0.2.0.dist-info/WHEEL
fluxpoint_py-0.2.0.dist-info/top_level.txt
fluxpoint_py-0.2.0.dist-info/RECORD
