Metadata-Version: 2.4
Name: fluxpoint.py
Version: 0.2.0
Summary: A Python wrapper for the Fluxpoint API
Home-page: https://github.com/Creatrix-Net/fluxpoint.py
Author: Dhruva Shaw
License: GNU GENERAL PUBLIC LICENSE
Project-URL: fluxpoint.py API wrapper Docs, https://fluxpointpy.dhruvashaw.in
Project-URL: Official Api Docs, https://docs.fluxpoint.dev/api
Project-URL: Get Api Token, https://fluxpoint.dev/api/access
Project-URL: Offcial Fluxpoint discord server, https://discord.gg/fluxpoint
Project-URL: Support server for api wrapper, https://discord.gg/vfXHwS3nmQ
Project-URL: Repository, https://github.com/Creatrix-Net/fluxpoint.py
Project-URL: Examples Directory, https://github.com/Creatrix-Net/fluxpoint.py/tree/master/examples
Project-URL: Issue tracker, https://github.com/Creatrix-Net/fluxpoint.py/issues
Keywords: fluxpoint api,api,wrapper,async wrapper
Classifier: Development Status :: 5 - Production/Stable
Classifier: License :: OSI Approved :: GNU General Public License v2 (GPLv2)
Classifier: Intended Audience :: Developers
Classifier: Natural Language :: English
Classifier: Operating System :: OS Independent
Classifier: Programming Language :: Python :: 3
Classifier: Programming Language :: Python :: 3.9
Classifier: Programming Language :: Python :: 3.10
Classifier: Programming Language :: Python :: 3.11
Classifier: Programming Language :: Python :: 3.12
Classifier: Topic :: Internet
Classifier: Topic :: Communications
Classifier: Topic :: Software Development :: Libraries
Classifier: Topic :: Software Development :: Libraries :: Python Modules
Classifier: Topic :: Utilities
Classifier: Typing :: Typed
Requires-Python: >=3.9
License-File: LICENSE
Requires-Dist: aiohttp>=3.8.1
Requires-Dist: yarl>=1.7.2
Provides-Extra: speed
Requires-Dist: aiohttp[speedups]>=3.8.1; extra == "speed"
Provides-Extra: docs
Requires-Dist: sphinx; extra == "docs"
Requires-Dist: sphinxcontrib_trio; extra == "docs"
Requires-Dist: sphinxcontrib-websupport; extra == "docs"
Requires-Dist: sphinx-autoapi; extra == "docs"
Requires-Dist: typing-extensions; extra == "docs"
Dynamic: author
Dynamic: classifier
Dynamic: description
Dynamic: description-content-type
Dynamic: home-page
Dynamic: keywords
Dynamic: license
Dynamic: license-file
Dynamic: project-url
Dynamic: provides-extra
Dynamic: requires-dist
Dynamic: requires-python
Dynamic: summary
